README.txt
setup.py
hmc_loss/__init__.py
hmc_loss/hmc_loss.py
hmc_loss.egg-info/PKG-INFO
hmc_loss.egg-info/SOURCES.txt
hmc_loss.egg-info/dependency_links.txt
hmc_loss.egg-info/requires.txt
hmc_loss.egg-info/top_level.txt