Metadata-Version: 1.1
Name: hmc-loss
Version: 1.0.0
Summary: UNKNOWN
Home-page: https://github.com/TaskeHAMANO/hmc_loss
Author: Shinya SUZUKI
Author-email: shinya.s.825@gmail.com
License: MIT
Keywords: validation,metrics,machine learning
Platform: UNKNOWN
Classifier: Programming Language :: Python
Classifier: Programming Language :: Python :: 3
Classifier: License :: OSI Approved :: MIT License
Classifier: Topic :: Scientific/Engineering :: Information Analysis
